MANIFEST.in
NEWS.txt
README.rst
setup.py
bin/maud4latlonnc
bin/maud4nc
maud/FilterUneven.py
maud/__init__.py
maud/core1D.py
maud/core2D.py
maud/core2Dlatlon.py
maud/distance.py
maud/distance.pyx
maud/maud.py
maud/maud.pyx
maud/tests_support.py
maud/window_func.py
maud/window_func.pyx
maud/window_func_scalar.pyx
maud.egg-info/PKG-INFO
maud.egg-info/SOURCES.txt
maud.egg-info/dependency_links.txt
maud.egg-info/not-zip-safe
maud.egg-info/requires.txt
maud.egg-info/top_level.txt