Metadata-Version: 1.1
Name: maud
Version: 0.9.2
Summary: Moving Average for Uneven Data
Home-page: http://maud.castelao.net
Author: Guilherme Castelao, Bia Villas-Boas, Luiz Irber
Author-email: guilherme@castelao.net, bia@melovillasboas.com, luiz.irber@gmail.com
License: PSF
Download-URL: http://pypi.python.org/packages/source/m/maud/maud-0.9.2.tar.gz
Platform: any
Classifier: Development Status :: 3 - Alpha
Classifier: Intended Audience :: Developers
Classifier: Intended Audience :: Science/Research
Classifier: License :: OSI Approved :: Python Software Foundation License
Classifier: Operating System :: OS Independent
Classifier: Programming Language :: Python :: 2
Classifier: Topic :: Scientific/Engineering
Classifier: Topic :: Software Development :: Libraries :: Python Modules
